PaymentAI/__init__.py
PaymentAI/core.py
paymentAI-0.1.11.dist-info/LICENSE
paymentAI-0.1.11.dist-info/METADATA
paymentAI-0.1.11.dist-info/WHEEL
paymentAI-0.1.11.dist-info/top_level.txt
paymentAI-0.1.11.dist-info/RECORD
