Metadata-Version: 2.2
Name: paymentAI
Version: 0.1.11
Summary: A package to handle transaction events and send payloads.
Home-page: https://github.com/AgentPaid/ap-client
Author: paymentAI
Author-email: janaka@agentpaid.ai
Classifier: Programming Language :: Python :: 3
Classifier: License :: OSI Approved :: MIT License
Classifier: Operating System :: OS Independent
Requires-Python: >=3.6
License-File: LICENSE
Requires-Dist: requests>=2.0.0
Dynamic: author
Dynamic: author-email
Dynamic: classifier
Dynamic: description
Dynamic: description-content-type
Dynamic: home-page
Dynamic: requires-dist
Dynamic: requires-python
Dynamic: summary
